docuglean/__init__.py
docuglean/extract.py
docuglean/ocr.py
docuglean/types.py
docuglean/utils.py
docuglean/providers/__init__.py
docuglean/providers/gemini.py
docuglean/providers/huggingface.py
docuglean/providers/mistral.py
docuglean/providers/openai.py
docuglean_ocr-1.0.0.dist-info/METADATA
docuglean_ocr-1.0.0.dist-info/WHEEL
docuglean_ocr-1.0.0.dist-info/licenses/LICENSE
docuglean_ocr-1.0.0.dist-info/RECORD
