Metadata-Version: 2.4
Name: docuglean-ocr
Version: 1.0.0
Summary: An SDK for intelligent document processing using SOTA VLLM models
Project-URL: Repository, https://github.com/docuglean-ai/docuglean-ocr
Project-URL: Issues, https://github.com/docuglean-ai/docuglean-ocr/issues
Author-email: docuglean-ai <contact@docuglean.ai>
License: Apache-2.0
License-File: LICENSE
Keywords: document,document-processing,llm,ocr,text-extraction
Requires-Python: >=3.11
Requires-Dist: google-genai>=1.32.0
Requires-Dist: httpx>=0.25.0
Requires-Dist: mistralai>=0.0.10
Requires-Dist: openai>=1.0.0
Requires-Dist: pydantic>=2.0.0
Requires-Dist: transformers>=4.0.0
Provides-Extra: dev
Requires-Dist: pytest-asyncio>=0.24.0; extra == 'dev'
Requires-Dist: pytest>=8.0.0; extra == 'dev'
Requires-Dist: ruff>=0.12.0; extra == 'dev'
